labdesk/__init__.py
labdesk/api/__init__.py
labdesk/api/init.py
labdesk/api/run.py
labdesk/api/show.py
labdesk/api/submit.py
labdesk/cli/main.py
labdesk/cli/manager.py
labdesk/cli/runner.py
labdesk/configs/config.py
labdesk/configs/config_commented.py
labdesk/scripts/manager.py
labdesk/scripts/pbs.sh
labdesk/scripts/runner.py
labdesk/scripts/show_jobs.py
labdesk/tui/log_table.py
labdesk/tui/log_viewer.css
labdesk/utils/config.py
labdesk/utils/git.py
labdesk/utils/logging.py
labdesk/utils/project.py
labdesk/utils/runner.py
labdesk-0.4.0.dist-info/METADATA
labdesk-0.4.0.dist-info/WHEEL
labdesk-0.4.0.dist-info/entry_points.txt
labdesk-0.4.0.dist-info/RECORD
