Metadata-Version: 2.3
Name: labdesk
Version: 0.4.0
Summary: Labdesk is a library created to support rapid and reproducible experimentation.
Author: Andrea Rosasco
Author-email: andrearosasco.ar@gmail.com
Requires-Python: >=3.8,<4.0
Classifier: Programming Language :: Python :: 3
Classifier: Programming Language :: Python :: 3.8
Classifier: Programming Language :: Python :: 3.9
Classifier: Programming Language :: Python :: 3.10
Classifier: Programming Language :: Python :: 3.11
Classifier: Programming Language :: Python :: 3.12
Classifier: Programming Language :: Python :: 3.13
Requires-Dist: typer (>=0,<1)
Project-URL: Homepage, https://github.com/andrearosasco/labdesk
Project-URL: Repository, https://github.com/andrearosasco/labdesk
